{"nameWithOwner": "twitter/the-algorithm", "reportID": "WEEKLY-REPORT-2023-04-10", "datestamp": {"latest": "2023-04-10", "previous": "2023-04-03"}, "data": {"commits": {"latest": 14, "previous": 3, "diff": 11}, "issues": {"latest": 737, "previous": 635, "diff": 102}, "openIssues": {"latest": 110, "previous": 198, "diff": -88}, "closedIssues": {"latest": 627, "previous": 437, "diff": 190}, "pullRequests": {"latest": 472, "previous": 375, "diff": 97}, "openPullRequests": {"latest": 187, "previous": 209, "diff": -22}, "mergedPullRequests": {"latest": 2, "previous": 0, "diff": 2}, "closedPullRequests": {"latest": 283, "previous": 166, "diff": 117}, "forkCount": {"latest": 10967, "previous": 7148, "diff": 3819}, "stargazers": {"latest": 53111, "previous": 38832, "diff": 14279}, "watchers": {"latest": 332, "previous": 278, "diff": 54}}}