{"nameWithOwner": "pantsbuild/pex", "reportID": "WEEKLY-REPORT-2018-09-28", "datestamp": {"latest": "2018-09-28", "previous": "2018-09-21"}, "data": {"commits": {"latest": 514, "previous": 510, "diff": 4}, "issues": {"latest": 324, "previous": 320, "diff": 4}, "openIssues": {"latest": 86, "previous": 86, "diff": 0}, "closedIssues": {"latest": 238, "previous": 234, "diff": 4}, "pullRequests": {"latest": 239, "previous": 230, "diff": 9}, "openPullRequests": {"latest": 18, "previous": 15, "diff": 3}, "mergedPullRequests": {"latest": 178, "previous": 174, "diff": 4}, "closedPullRequests": {"latest": 43, "previous": 41, "diff": 2}, "forkCount": {"latest": 125, "previous": 123, "diff": 2}, "stargazers": {"latest": 1106, "previous": 1103, "diff": 3}, "watchers": {"latest": 46, "previous": 46, "diff": 0}}}