{"name": "twitterdev", "reportID": "WEEKLY-REPORT-2019-12-27", "datestamp": {"latest": "2019-12-27", "previous": "2019-12-20"}, "data": {"commits": {"latest": 4067, "previous": 4066, "diff_breakdown": {"twitter-python-ads-sdk": 1}, "diff": 1}, "issues": {"latest": 315, "previous": 313, "diff_breakdown": {"twitter-ruby-ads-sdk": 2}, "diff": 2}, "openIssues": {"latest": 98, "previous": 101, "diff_breakdown": {"twitter-ruby-ads-sdk": 1, "twitter-python-ads-sdk": -4}, "diff": -3}, "closedIssues": {"latest": 217, "previous": 212, "diff_breakdown": {"twitter-ruby-ads-sdk": 1, "twitter-python-ads-sdk": 4}, "diff": 5}, "pullRequests": {"latest": 518, "previous": 515, "diff_breakdown": {"twitter-ruby-ads-sdk": 1, "twitter-python-ads-sdk": 2}, "diff": 3}, "openPullRequests": {"latest": 36, "previous": 34, "diff_breakdown": {"twitter-ruby-ads-sdk": 1, "twitter-python-ads-sdk": 1}, "diff": 2}, "mergedPullRequests": {"latest": 412, "previous": 411, "diff_breakdown": {"twitter-python-ads-sdk": 1}, "diff": 1}, "closedPullRequests": {"latest": 70, "previous": 70, "diff_breakdown": {}, "diff": 0}, "forkCount": {"latest": 1156, "previous": 1152, "diff_breakdown": {"do_more_with_twitter_data": 2, "twitter-ruby-ads-sdk": 1, "account-activity-dashboard": 1}, "diff": 4}, "stargazers": {"latest": 2063, "previous": 2053, "diff_breakdown": {"do_more_with_twitter_data": 4, "SnowBotDev": 1, "search-tweets-python": 3, "twitter-ruby-ads-sdk": 1, "account-activity-dashboard": -1, "twitter-python-ads-sdk": 1, "large-video-upload-python": 1}, "diff": 10}, "watchers": {"latest": 1036, "previous": 1034, "diff_breakdown": {"do_more_with_twitter_data": 1, "twitter-webhook-boilerplate-node": 1}, "diff": 2}}, "highlights": [], "no_of_repos": 71}