{"nameWithOwner": "twitter/opensource-website", "reportID": "WEEKLY-REPORT-2022-05-23", "datestamp": {"latest": "2022-05-23", "previous": "2022-05-16"}, "data": {"commits": {"latest": 916, "previous": 915, "diff": 1}, "issues": {"latest": 45, "previous": 45, "diff": 0}, "openIssues": {"latest": 4, "previous": 4, "diff": 0}, "closedIssues": {"latest": 41, "previous": 41, "diff": 0}, "pullRequests": {"latest": 58, "previous": 58, "diff": 0}, "openPullRequests": {"latest": 1, "previous": 1, "diff": 0}, "mergedPullRequests": {"latest": 25, "previous": 25, "diff": 0}, "closedPullRequests": {"latest": 32, "previous": 32, "diff": 0}, "forkCount": {"latest": 596, "previous": 596, "diff": 0}, "stargazers": {"latest": 1865, "previous": 1861, "diff": 4}, "watchers": {"latest": 443, "previous": 443, "diff": 0}}}