{"nameWithOwner": "twitter/hpack", "reportID": "MONTHLY-2018-07-27", "datestamp": {"this_month": "2018-07-27", "last_month": "2018-06-29"}, "data": {"commits": {"this_month": 61, "last_month": 61, "diff": 0}, "forkCount": {"this_month": 37, "last_month": 37, "diff": 0}, "issues": {"this_month": 12, "last_month": 12, "diff": 0}, "openIssues": {"this_month": 3, "last_month": 3, "diff": 0}, "closedIssues": {"this_month": 9, "last_month": 9, "diff": 0}, "pullRequests": {"this_month": 20, "last_month": 20, "diff": 0}, "openPullRequests": {"this_month": 3, "last_month": 3, "diff": 0}, "mergedPullRequests": {"this_month": 6, "last_month": 6, "diff": 0}, "closedPullRequests": {"this_month": 11, "last_month": 11, "diff": 0}, "stargazers": {"this_month": 146, "last_month": 146, "diff": 0}, "watchers": {"this_month": 138, "last_month": 138, "diff": 0}}}