{"nameWithOwner": "twitterdev/twitter-api-typescript-sdk", "reportID": "WEEKLY-REPORT-2022-03-28", "datestamp": {"latest": "2022-03-28", "previous": "2022-03-21"}, "data": {"commits": {"latest": 9, "previous": 4, "diff": 5}, "issues": {"latest": 0, "previous": 0, "diff": 0}, "openIssues": {"latest": 0, "previous": 0, "diff": 0}, "closedIssues": {"latest": 0, "previous": 0, "diff": 0}, "pullRequests": {"latest": 3, "previous": 1, "diff": 2}, "openPullRequests": {"latest": 0, "previous": 0, "diff": 0}, "mergedPullRequests": {"latest": 3, "previous": 1, "diff": 2}, "closedPullRequests": {"latest": 0, "previous": 0, "diff": 0}, "forkCount": {"latest": 6, "previous": 3, "diff": 3}, "stargazers": {"latest": 337, "previous": 271, "diff": 66}, "watchers": {"latest": 26, "previous": 25, "diff": 1}}}