{"nameWithOwner": "twitter/pelikan", "reportID": "MONTHLY-REPORT-2022-02-07", "datestamp": {"latest": "2022-02-07", "previous": "2022-01-10"}, "data": {"commits": {"latest": 728, "previous": 717, "diff": 11}, "issues": {"latest": 96, "previous": 94, "diff": 2}, "openIssues": {"latest": 40, "previous": 38, "diff": 2}, "closedIssues": {"latest": 56, "previous": 56, "diff": 0}, "pullRequests": {"latest": 298, "previous": 293, "diff": 5}, "openPullRequests": {"latest": 9, "previous": 15, "diff": -6}, "mergedPullRequests": {"latest": 271, "previous": 260, "diff": 11}, "closedPullRequests": {"latest": 18, "previous": 18, "diff": 0}, "forkCount": {"latest": 91, "previous": 90, "diff": 1}, "stargazers": {"latest": 968, "previous": 947, "diff": 21}, "watchers": {"latest": 41, "previous": 40, "diff": 1}}}