{"nameWithOwner": "twitter/pelikan", "reportID": "WEEKLY-REPORT-2021-09-27", "datestamp": {"latest": "2021-09-27", "previous": "2021-09-20"}, "data": {"commits": {"latest": 684, "previous": 683, "diff": 1}, "issues": {"latest": 86, "previous": 85, "diff": 1}, "openIssues": {"latest": 32, "previous": 31, "diff": 1}, "closedIssues": {"latest": 54, "previous": 54, "diff": 0}, "pullRequests": {"latest": 255, "previous": 255, "diff": 0}, "openPullRequests": {"latest": 7, "previous": 8, "diff": -1}, "mergedPullRequests": {"latest": 230, "previous": 229, "diff": 1}, "closedPullRequests": {"latest": 18, "previous": 18, "diff": 0}, "forkCount": {"latest": 84, "previous": 83, "diff": 1}, "stargazers": {"latest": 783, "previous": 765, "diff": 18}, "watchers": {"latest": 40, "previous": 40, "diff": 0}}}