{"nameWithOwner": "twitter/summingbird", "reportID": "WEEKLY-2018-06-29", "datestamp": {"this_week": "2018-06-29", "last_week": "2018-06-22"}, "data": {"commits": {"this_week": 1785, "last_week": 1785, "diff": 0}, "issues": {"this_week": 281, "last_week": 281, "diff": 0}, "openIssues": {"this_week": 147, "last_week": 147, "diff": 0}, "closedIssues": {"this_week": 134, "last_week": 134, "diff": 0}, "pullRequests": {"this_week": 484, "last_week": 484, "diff": 0}, "openPullRequests": {"this_week": 12, "last_week": 12, "diff": 0}, "mergedPullRequests": {"this_week": 426, "last_week": 426, "diff": 0}, "closedPullRequests": {"this_week": 46, "last_week": 46, "diff": 0}, "forkCount": {"this_week": 261, "last_week": 261, "diff": 0}, "stargazers": {"this_week": 1959, "last_week": 1958, "diff": 1}, "watchers": {"this_week": 314, "last_week": 314, "diff": 0}}}