{"okapies": {"name": "Yuta Okamoto", "user": 201926, "commits": 61.0, "issues": 3.0, "commit_comments": 0.0, "issue_comments": 6.0, "pull_requests": 0.0, "pull_request_comments": 0.0, "total": 70.0, "login": "okapies", "avatarUrl": "https://avatars2.githubusercontent.com/u/657642?v=4", "isHireable": false, "company": "Preferred Networks, inc.", "location": "Tokyo", "url": "https://github.com/okapies"}, "mariusae": {"name": "marius a. eriksen", "user": 5437425, "commits": 13.0, "issues": 0.0, "commit_comments": 0.0, "issue_comments": 12.0, "pull_requests": 0.0, "pull_request_comments": 0.0, "total": 25.0, "login": "mariusae", "avatarUrl": "https://avatars2.githubusercontent.com/u/32104?v=4", "isHireable": false, "company": "@grailbio", "location": "mp, ca", "url": "https://github.com/mariusae"}, "yau-ref": {"name": "Yau Ref", "user": 986165, "commits": 19.0, "issues": 1.0, "commit_comments": 0.0, "issue_comments": 2.0, "pull_requests": 0.0, "pull_request_comments": 0.0, "total": 22.0, "login": "yau-ref", "avatarUrl": "https://avatars0.githubusercontent.com/u/2406259?v=4", "isHireable": false, "company": null, "location": null, "url": "https://github.com/yau-ref"}, "mosesn": {"name": "Moses Nakamura", "user": 132262, "commits": 2.0, "issues": 0.0, "commit_comments": 0.0, "issue_comments": 17.0, "pull_requests": 0.0, "pull_request_comments": 0.0, "total": 19.0, "login": "mosesn", "avatarUrl": "https://avatars3.githubusercontent.com/u/156562?v=4", "isHireable": false, "company": "Twitter", "location": "SF", "url": "https://github.com/mosesn"}, "appigram": {"name": "Evgeny Sysmanov", "user": 614625, "commits": 14.0, "issues": 1.0, "commit_comments": 0.0, "issue_comments": 1.0, "pull_requests": 0.0, "pull_request_comments": 0.0, "total": 16.0, "login": "appigram", "avatarUrl": "https://avatars0.githubusercontent.com/u/2223582?v=4", "isHireable": true, "company": "Ryfma", "location": null, "url": "https://github.com/appigram"}, "hongjiang": {"name": "hongjiang", "user": 104822, "commits": 6.0, "issues": 1.0, "commit_comments": 1.0, "issue_comments": 0.0, "pull_requests": 0.0, "pull_request_comments": 0.0, "total": 8.0, "login": "hongjiang", "avatarUrl": "https://avatars2.githubusercontent.com/u/822582?v=4", "isHireable": false, "company": "Alibaba", "location": "hangzhou", "url": "https://github.com/hongjiang"}, "gdickinson": {"name": "Guy Dickinson", "user": 365017, "commits": 6.0, "issues": 0.0, "commit_comments": 0.0, "issue_comments": 2.0, "pull_requests": 0.0, "pull_request_comments": 0.0, "total": 8.0, "login": "gdickinson", "avatarUrl": "https://avatars1.githubusercontent.com/u/1130928?v=4", "isHireable": false, "company": "Twitter", "location": "New York, NY", "url": "https://github.com/gdickinson"}, "benpence": {"name": "Ben Pence", "user": 401065, "commits": 2.0, "issues": 0.0, "commit_comments": 0.0, "issue_comments": 5.0, "pull_requests": 0.0, "pull_request_comments": 0.0, "total": 7.0, "login": "benpence", "avatarUrl": "https://avatars3.githubusercontent.com/u/736903?v=4", "isHireable": false, "company": null, "location": null, "url": "https://github.com/benpence"}, "web-flow": {"name": "GitHub Web Flow", "user": 30351173, "commits": 7.0, "issues": 0.0, "commit_comments": 0.0, "issue_comments": 0.0, "pull_requests": 0.0, "pull_request_comments": 0.0, "total": 7.0, "login": "web-flow", "avatarUrl": "https://avatars3.githubusercontent.com/u/19864447?v=4", "isHireable": false, "company": "", "location": null, "url": "https://github.com/web-flow"}, "kevinoliver": {"name": "Kevin Oliver", "user": 64314, "commits": 2.0, "issues": 1.0, "commit_comments": 0.0, "issue_comments": 4.0, "pull_requests": 0.0, "pull_request_comments": 0.0, "total": 7.0, "login": "kevinoliver", "avatarUrl": "https://avatars2.githubusercontent.com/u/347229?v=4", "isHireable": false, "company": "@twitter ", "location": "San Francisco", "url": "https://github.com/kevinoliver"}, "lispking": {"name": "", "user": 2864675, "commits": 6.0, "issues": 0.0, "commit_comments": 0.0, "issue_comments": 0.0, "pull_requests": 0.0, "pull_request_comments": 0.0, "total": 6.0, "login": "lispking", "avatarUrl": "https://avatars2.githubusercontent.com/u/4446580?v=4", "isHireable": false, "company": "Alibaba", "location": "Hangzhou, China", "url": "https://github.com/lispking"}, "thorade": {"name": "Matthis Thorade", "user": 402159, "commits": 3.0, "issues": 1.0, "commit_comments": 0.0, "issue_comments": 2.0, "pull_requests": 0.0, "pull_request_comments": 0.0, "total": 6.0, "login": "thorade", "avatarUrl": "https://avatars2.githubusercontent.com/u/314571?v=4", "isHireable": false, "company": "@modelon", "location": null, "url": "https://github.com/thorade"}, "jeremieSimon": {"name": "jeremie", "user": 215383, "commits": 1.0, "issues": 1.0, "commit_comments": 0.0, "issue_comments": 3.0, "pull_requests": 0.0, "pull_request_comments": 0.0, "total": 5.0, "login": "jeremieSimon", "avatarUrl": "https://avatars2.githubusercontent.com/u/614919?v=4", "isHireable": false, "company": "", "location": "San Francisco", "url": "https://github.com/jeremieSimon"}, "lahosken": {"name": "Larry Hosken", "user": 418424, "commits": 1.0, "issues": 0.0, "commit_comments": 1.0, "issue_comments": 3.0, "pull_requests": 0.0, "pull_request_comments": 0.0, "total": 5.0, "login": "lahosken", "avatarUrl": "https://avatars0.githubusercontent.com/u/371906?v=4", "isHireable": false, "company": "", "location": "San Francisco, USA", "url": "https://github.com/lahosken"}, "SBozhko": {"name": "Svetlana Bozhko", "user": 314181, "commits": 3.0, "issues": 1.0, "commit_comments": 0.0, "issue_comments": 0.0, "pull_requests": 0.0, "pull_request_comments": 0.0, "total": 4.0, "login": "SBozhko", "avatarUrl": "https://avatars2.githubusercontent.com/u/1653130?v=4", "isHireable": true, "company": "", "location": "London", "url": "https://github.com/SBozhko"}, "jon-ruckwood": {"name": "Jonathan Ruckwood", "user": 466484, "commits": 0.0, "issues": 2.0, "commit_comments": 0.0, "issue_comments": 2.0, "pull_requests": 0.0, "pull_request_comments": 0.0, "total": 4.0, "login": "jon-ruckwood", "avatarUrl": "https://avatars0.githubusercontent.com/u/435298?v=4", "isHireable": false, "company": null, "location": "London, England", "url": "https://github.com/jon-ruckwood"}, "akiomik": {"name": "Akiomi KAMAKURA", "user": 404867, "commits": 1.0, "issues": 2.0, "commit_comments": 0.0, "issue_comments": 1.0, "pull_requests": 0.0, "pull_request_comments": 0.0, "total": 4.0, "login": "akiomik", "avatarUrl": "https://avatars0.githubusercontent.com/u/1457682?v=4", "isHireable": true, "company": "", "location": "Tokyo, JAPAN", "url": "https://github.com/akiomik"}, "pvorb": {"name": "Paul Vorbach", "user": 5132, "commits": 1.0, "issues": 2.0, "commit_comments": 0.0, "issue_comments": 1.0, "pull_requests": 0.0, "pull_request_comments": 0.0, "total": 4.0, "login": "pvorb", "avatarUrl": "https://avatars3.githubusercontent.com/u/183534?v=4", "isHireable": false, "company": "@deviceinsight", "location": null, "url": "https://github.com/pvorb"}, "jeffstyr": {"name": "Jeff Clites", "user": 78044, "commits": 2.0, "issues": 2.0, "commit_comments": 0.0, "issue_comments": 0.0, "pull_requests": 0.0, "pull_request_comments": 0.0, "total": 4.0, "login": "jeffstyr", "avatarUrl": "https://avatars0.githubusercontent.com/u/542980?v=4", "isHireable": false, "company": null, "location": "San Jose, CA", "url": "https://github.com/jeffstyr"}, "tongqqiu": {"name": "Tongqing Qiu", "user": 2367610, "commits": 2.0, "issues": 0.0, "commit_comments": 1.0, "issue_comments": 1.0, "pull_requests": 0.0, "pull_request_comments": 0.0, "total": 4.0, "login": "tongqqiu", "avatarUrl": "https://avatars3.githubusercontent.com/u/5096700?v=4", "isHireable": false, "company": "", "location": "Alpharetta, GA", "url": "https://github.com/tongqqiu"}, "peixy0": {"name": "", "user": 6063194, "commits": 2.0, "issues": 0.0, "commit_comments": 0.0, "issue_comments": 1.0, "pull_requests": 0.0, "pull_request_comments": 0.0, "total": 3.0, "login": "peixy0", "avatarUrl": "https://avatars2.githubusercontent.com/u/1408349?v=4", "isHireable": true, "company": "", "location": "Hangzhou, Zhejiang, China", "url": "https://github.com/peixy0"}, "jjinux": {"name": "Shannon -jj Behrens", "user": 320566, "commits": 0.0, "issues": 0.0, "commit_comments": 0.0, "issue_comments": 3.0, "pull_requests": 0.0, "pull_request_comments": 0.0, "total": 3.0, "login": "jjinux", "avatarUrl": "https://avatars1.githubusercontent.com/u/74551?v=4", "isHireable": false, "company": "Self", "location": "Concord, CA", "url": "https://github.com/jjinux"}, "randrewj": {"name": null, "user": 3086535, "commits": 1.0, "issues": 0.0, "commit_comments": 0.0, "issue_comments": 2.0, "pull_requests": 0.0, "pull_request_comments": 0.0, "total": 3.0, "login": "randrewj", "avatarUrl": "https://avatars2.githubusercontent.com/u/5279006?v=4", "isHireable": false, "company": null, "location": null, "url": "https://github.com/randrewj"}, "stnly": {"name": "stnly", "user": 165256, "commits": 3.0, "issues": 0.0, "commit_comments": 0.0, "issue_comments": 0.0, "pull_requests": 0.0, "pull_request_comments": 0.0, "total": 3.0, "login": "stnly", "avatarUrl": "https://avatars2.githubusercontent.com/u/1204671?v=4", "isHireable": true, "company": "@cloudflare", "location": null, "url": "https://github.com/stnly"}, "sumkincpp": {"name": "Fedor Sumkin", "user": 41293, "commits": 1.0, "issues": 1.0, "commit_comments": 0.0, "issue_comments": 1.0, "pull_requests": 0.0, "pull_request_comments": 0.0, "total": 3.0, "login": "sumkincpp", "avatarUrl": "https://avatars2.githubusercontent.com/u/738925?v=4", "isHireable": false, "company": "", "location": "Moscow, RU", "url": "https://github.com/sumkincpp"}, "orrsella": {"name": "Orr Sella", "user": 419341, "commits": 2.0, "issues": 1.0, "commit_comments": 0.0, "issue_comments": 0.0, "pull_requests": 0.0, "pull_request_comments": 0.0, "total": 3.0, "login": "orrsella", "avatarUrl": "https://avatars1.githubusercontent.com/u/1591876?v=4", "isHireable": false, "company": "Facebook", "location": "San Francisco Bay Area", "url": "https://github.com/orrsella"}, "mattknox": {"name": "matt knox", "user": 2579, "commits": 1.0, "issues": 1.0, "commit_comments": 0.0, "issue_comments": 0.0, "pull_requests": 0.0, "pull_request_comments": 0.0, "total": 2.0, "login": "mattknox", "avatarUrl": "https://avatars2.githubusercontent.com/u/2965?v=4", "isHireable": false, "company": "twitter", "location": "san francisco, ca", "url": "https://github.com/mattknox"}, "stuhood": {"name": "Stu Hood", "user": 51152, "commits": 1.0, "issues": 0.0, "commit_comments": 0.0, "issue_comments": 1.0, "pull_requests": 0.0, "pull_request_comments": 0.0, "total": 2.0, "login": "stuhood", "avatarUrl": "https://avatars1.githubusercontent.com/u/46740?v=4", "isHireable": false, "company": "Twitter", "location": "San Francisco", "url": "https://github.com/stuhood"}, "pavlov99": {"name": "Kirill Pavlov", "user": 622216, "commits": 1.0, "issues": 1.0, "commit_comments": 0.0, "issue_comments": 0.0, "pull_requests": 0.0, "pull_request_comments": 0.0, "total": 2.0, "login": "pavlov99", "avatarUrl": "https://avatars1.githubusercontent.com/u/590293?v=4", "isHireable": true, "company": "@Terminal1", "location": "Hong Kong", "url": "https://github.com/pavlov99"}, "adamv": {"name": "Adam Vandenberg", "user": 7214, "commits": 1.0, "issues": 1.0, "commit_comments": 0.0, "issue_comments": 0.0, "pull_requests": 0.0, "pull_request_comments": 0.0, "total": 2.0, "login": "adamv", "avatarUrl": "https://avatars0.githubusercontent.com/u/3566?v=4", "isHireable": false, "company": "", "location": "Issaquah, WA", "url": "https://github.com/adamv"}, "gurghet": {"name": "Andrea Passaglia", "user": 619902, "commits": 0.0, "issues": 1.0, "commit_comments": 0.0, "issue_comments": 1.0, "pull_requests": 0.0, "pull_request_comments": 0.0, "total": 2.0, "login": "gurghet", "avatarUrl": "https://avatars3.githubusercontent.com/u/420735?v=4", "isHireable": true, "company": "GG&Q", "location": "Genova", "url": "https://github.com/gurghet"}, "serithemage": {"name": "Charlie Dohyun Jung", "user": 1555009, "commits": 0.0, "issues": 1.0, "commit_comments": 0.0, "issue_comments": 1.0, "pull_requests": 0.0, "pull_request_comments": 0.0, "total": 2.0, "login": "serithemage", "avatarUrl": "https://avatars0.githubusercontent.com/u/3435720?v=4", "isHireable": false, "company": "Amazon Web Services", "location": "Seoul Korea", "url": "https://github.com/serithemage"}, "benolee": {"name": "Ben Holley", "user": 99949, "commits": 1.0, "issues": 1.0, "commit_comments": 0.0, "issue_comments": 0.0, "pull_requests": 0.0, "pull_request_comments": 0.0, "total": 2.0, "login": "benolee", "avatarUrl": "https://avatars3.githubusercontent.com/u/384535?v=4", "isHireable": false, "company": "", "location": null, "url": "https://github.com/benolee"}, "caniszczyk": {"name": "Chris Aniszczyk", "user": 12202, "commits": 0.0, "issues": 0.0, "commit_comments": 0.0, "issue_comments": 2.0, "pull_requests": 0.0, "pull_request_comments": 0.0, "total": 2.0, "login": "caniszczyk", "avatarUrl": "https://avatars1.githubusercontent.com/u/63777?v=4", "isHireable": false, "company": "", "location": "Austin, TX USA", "url": "https://github.com/caniszczyk"}, "Fleurer": {"name": "flaneur", "user": 54905, "commits": 1.0, "issues": 1.0, "commit_comments": 0.0, "issue_comments": 0.0, "pull_requests": 0.0, "pull_request_comments": 0.0, "total": 2.0, "login": "Fleurer", "avatarUrl": "https://avatars3.githubusercontent.com/u/129800?v=4", "isHireable": true, "company": "", "location": "Beijing", "url": "https://github.com/Fleurer"}, "jdanbrown": {"name": "Dan Brown", "user": 30433, "commits": 1.0, "issues": 1.0, "commit_comments": 0.0, "issue_comments": 0.0, "pull_requests": 0.0, "pull_request_comments": 0.0, "total": 2.0, "login": "jdanbrown", "avatarUrl": "https://avatars1.githubusercontent.com/u/627486?v=4", "isHireable": false, "company": "", "location": "SF", "url": "https://github.com/jdanbrown"}, "anson0370": {"name": "Anson Chan", "user": 103334, "commits": 1.0, "issues": 0.0, "commit_comments": 0.0, "issue_comments": 0.0, "pull_requests": 0.0, "pull_request_comments": 0.0, "total": 1.0, "login": "anson0370", "avatarUrl": "https://avatars0.githubusercontent.com/u/283559?v=4", "isHireable": false, "company": "Terminus.io", "location": "Hangzhou. China", "url": "https://github.com/anson0370"}, "jondkoon": {"name": "Jon Koon", "user": 490990, "commits": 1.0, "issues": 0.0, "commit_comments": 0.0, "issue_comments": 0.0, "pull_requests": 0.0, "pull_request_comments": 0.0, "total": 1.0, "login": "jondkoon", "avatarUrl": "https://avatars2.githubusercontent.com/u/297508?v=4", "isHireable": false, "company": "Twitter, Inc.", "location": "San Francisco, CA", "url": "https://github.com/jondkoon"}, "jimschubert": {"name": "Jim Schubert", "user": 12573, "commits": 0.0, "issues": 0.0, "commit_comments": 0.0, "issue_comments": 1.0, "pull_requests": 0.0, "pull_request_comments": 0.0, "total": 1.0, "login": "jimschubert", "avatarUrl": "https://avatars2.githubusercontent.com/u/109659?v=4", "isHireable": true, "company": "", "location": "Richmond, VA", "url": "https://github.com/jimschubert"}, "sungjk": {"name": "Jeremy Kim", "user": 35472329, "commits": 0.0, "issues": 0.0, "commit_comments": 0.0, "issue_comments": 1.0, "pull_requests": 0.0, "pull_request_comments": 0.0, "total": 1.0, "login": "sungjk", "avatarUrl": "https://avatars0.githubusercontent.com/u/9454446?v=4", "isHireable": false, "company": "", "location": "Seoul. Korea", "url": "https://github.com/sungjk"}, "evnm": {"name": "Evan Meagher", "user": 61365, "commits": 1.0, "issues": 0.0, "commit_comments": 0.0, "issue_comments": 0.0, "pull_requests": 0.0, "pull_request_comments": 0.0, "total": 1.0, "login": "evnm", "avatarUrl": "https://avatars1.githubusercontent.com/u/110020?v=4", "isHireable": false, "company": "X", "location": "Oakland, CA", "url": "https://github.com/evnm"}, "clasnake": {"name": "clasnake", "user": 896171, "commits": 1.0, "issues": 0.0, "commit_comments": 0.0, "issue_comments": 0.0, "pull_requests": 0.0, "pull_request_comments": 0.0, "total": 1.0, "login": "clasnake", "avatarUrl": "https://avatars3.githubusercontent.com/u/1590497?v=4", "isHireable": false, "company": "eBay", "location": "Shanghai", "url": "https://github.com/clasnake"}, "marcel": {"name": "Marcel Molina", "user": 15445, "commits": 1.0, "issues": 0.0, "commit_comments": 0.0, "issue_comments": 0.0, "pull_requests": 0.0, "pull_request_comments": 0.0, "total": 1.0, "login": "marcel", "avatarUrl": "https://avatars3.githubusercontent.com/u/245?v=4", "isHireable": false, "company": "", "location": "San Francisco, CA", "url": "https://github.com/marcel"}, "timf": {"name": "Tim Freeman", "user": 36085, "commits": 0.0, "issues": 1.0, "commit_comments": 0.0, "issue_comments": 0.0, "pull_requests": 0.0, "pull_request_comments": 0.0, "total": 1.0, "login": "timf", "avatarUrl": "https://avatars3.githubusercontent.com/u/55415?v=4", "isHireable": false, "company": "", "location": "Seattle area", "url": "https://github.com/timf"}, "CLAassistant": {"name": "", "user": 7611120, "commits": 0.0, "issues": 0.0, "commit_comments": 0.0, "issue_comments": 1.0, "pull_requests": 0.0, "pull_request_comments": 0.0, "total": 1.0, "login": "CLAassistant", "avatarUrl": "https://avatars1.githubusercontent.com/u/11571300?v=4", "isHireable": false, "company": "", "location": null, "url": "https://github.com/CLAassistant"}, "berngp": {"name": "Bernardo Gomez Palacio", "user": 45877, "commits": 1.0, "issues": 0.0, "commit_comments": 0.0, "issue_comments": 0.0, "pull_requests": 0.0, "pull_request_comments": 0.0, "total": 1.0, "login": "berngp", "avatarUrl": "https://avatars0.githubusercontent.com/u/134985?v=4", "isHireable": false, "company": "", "location": "Foster City CA, USA", "url": "https://github.com/berngp"}, "andrewbts": {"name": null, "user": 284620, "commits": 1.0, "issues": 0.0, "commit_comments": 0.0, "issue_comments": 0.0, "pull_requests": 0.0, "pull_request_comments": 0.0, "total": 1.0, "login": "andrewbts", "avatarUrl": "https://avatars3.githubusercontent.com/u/2001761?v=4", "isHireable": false, "company": null, "location": null, "url": "https://github.com/andrewbts"}, "rand0m86": {"name": "Vitalii Mahas", "user": 2584526, "commits": 1.0, "issues": 0.0, "commit_comments": 0.0, "issue_comments": 0.0, "pull_requests": 0.0, "pull_request_comments": 0.0, "total": 1.0, "login": "rand0m86", "avatarUrl": "https://avatars0.githubusercontent.com/u/5267663?v=4", "isHireable": false, "company": "", "location": null, "url": "https://github.com/rand0m86"}, "evanj": {"name": "Evan Jones", "user": 156974, "commits": 0.0, "issues": 1.0, "commit_comments": 0.0, "issue_comments": 0.0, "pull_requests": 0.0, "pull_request_comments": 0.0, "total": 1.0, "login": "evanj", "avatarUrl": "https://avatars2.githubusercontent.com/u/675151?v=4", "isHireable": false, "company": null, "location": "New York, NY, USA", "url": "https://github.com/evanj"}, "ogandit": {"name": "Olivier Gandit", "user": 11627651, "commits": 0.0, "issues": 0.0, "commit_comments": 0.0, "issue_comments": 1.0, "pull_requests": 0.0, "pull_request_comments": 0.0, "total": 1.0, "login": "ogandit", "avatarUrl": "https://avatars0.githubusercontent.com/u/16599192?v=4", "isHireable": false, "company": "Cloudator", "location": "Helsinki", "url": "https://github.com/ogandit"}, "responsible": {"name": "Shihao Yan", "user": 6534479, "commits": 1.0, "issues": 0.0, "commit_comments": 0.0, "issue_comments": 0.0, "pull_requests": 0.0, "pull_request_comments": 0.0, "total": 1.0, "login": "responsible", "avatarUrl": "https://avatars2.githubusercontent.com/u/9255356?v=4", "isHireable": true, "company": "ThoughtWorks", "location": null, "url": "https://github.com/responsible"}, "vkostyukov": {"name": "Vladimir Kostyukov", "user": 72999, "commits": 0.0, "issues": 0.0, "commit_comments": 0.0, "issue_comments": 1.0, "pull_requests": 0.0, "pull_request_comments": 0.0, "total": 1.0, "login": "vkostyukov", "avatarUrl": "https://avatars1.githubusercontent.com/u/1098539?v=4", "isHireable": false, "company": "Twitter", "location": "San Francisco, CA", "url": "https://github.com/vkostyukov"}, "oscarindigo": {"name": null, "user": 578869, "commits": 0.0, "issues": 1.0, "commit_comments": 0.0, "issue_comments": 0.0, "pull_requests": 0.0, "pull_request_comments": 0.0, "total": 1.0, "login": "oscarindigo", "avatarUrl": "https://avatars0.githubusercontent.com/u/1770905?v=4", "isHireable": false, "company": null, "location": null, "url": "https://github.com/oscarindigo"}, "eed3si9n": {"name": "eugene yokota", "user": 4577, "commits": 0.0, "issues": 0.0, "commit_comments": 0.0, "issue_comments": 0.0, "pull_requests": 1.0, "pull_request_comments": 0.0, "total": 1.0, "login": "eed3si9n", "avatarUrl": "https://avatars0.githubusercontent.com/u/184683?v=4", "isHireable": false, "company": "@lightbend ", "location": "Amherst, MA", "url": "https://github.com/eed3si9n"}, "travisbrown": {"name": "Travis Brown", "user": 146404, "commits": 1.0, "issues": 0.0, "commit_comments": 0.0, "issue_comments": 0.0, "pull_requests": 0.0, "pull_request_comments": 0.0, "total": 1.0, "login": "travisbrown", "avatarUrl": "https://avatars3.githubusercontent.com/u/316049?v=4", "isHireable": true, "company": "@stripe", "location": "Santa Monica, CA", "url": "https://github.com/travisbrown"}, "tanimoto": {"name": "Paulo Tanimoto", "user": 725070, "commits": 1.0, "issues": 0.0, "commit_comments": 0.0, "issue_comments": 0.0, "pull_requests": 0.0, "pull_request_comments": 0.0, "total": 1.0, "login": "tanimoto", "avatarUrl": "https://avatars3.githubusercontent.com/u/5770?v=4", "isHireable": false, "company": "", "location": null, "url": "https://github.com/tanimoto"}, "oxcarh": {"name": "Oscar Hernandez", "user": 1522592, "commits": 0.0, "issues": 0.0, "commit_comments": 0.0, "issue_comments": 1.0, "pull_requests": 0.0, "pull_request_comments": 0.0, "total": 1.0, "login": "oxcarh", "avatarUrl": "https://avatars3.githubusercontent.com/u/2067516?v=4", "isHireable": false, "company": "@copili ", "location": "Mexico City", "url": "https://github.com/oxcarh"}, "xuwei-k": {"name": "kenji yoshida", "user": 8973, "commits": 1.0, "issues": 0.0, "commit_comments": 0.0, "issue_comments": 0.0, "pull_requests": 0.0, "pull_request_comments": 0.0, "total": 1.0, "login": "xuwei-k", "avatarUrl": "https://avatars0.githubusercontent.com/u/389787?v=4", "isHireable": false, "company": "", "location": "Tokyo", "url": "https://github.com/xuwei-k"}, "paulfryzel": {"name": "Paul Fryzel", "user": 9483, "commits": 0.0, "issues": 1.0, "commit_comments": 0.0, "issue_comments": 0.0, "pull_requests": 0.0, "pull_request_comments": 0.0, "total": 1.0, "login": "paulfryzel", "avatarUrl": "https://avatars3.githubusercontent.com/u/156808?v=4", "isHireable": false, "company": "Cond\u00e9 Nast", "location": "NYC", "url": "https://github.com/paulfryzel"}, "alcortaj": {"name": "JA", "user": 7806492, "commits": 0.0, "issues": 1.0, "commit_comments": 0.0, "issue_comments": 0.0, "pull_requests": 0.0, "pull_request_comments": 0.0, "total": 1.0, "login": "alcortaj", "avatarUrl": "https://avatars1.githubusercontent.com/u/5826080?v=4", "isHireable": false, "company": "", "location": null, "url": "https://github.com/alcortaj"}, "SethMilliken": {"name": "Seth Milliken", "user": 42089, "commits": 1.0, "issues": 0.0, "commit_comments": 0.0, "issue_comments": 0.0, "pull_requests": 0.0, "pull_request_comments": 0.0, "total": 1.0, "login": "SethMilliken", "avatarUrl": "https://avatars3.githubusercontent.com/u/282102?v=4", "isHireable": false, "company": "", "location": "Berkeley, CA", "url": "https://github.com/SethMilliken"}, "sorra": {"name": "Dongqing Hu", "user": 258079, "commits": 1.0, "issues": 0.0, "commit_comments": 0.0, "issue_comments": 0.0, "pull_requests": 0.0, "pull_request_comments": 0.0, "total": 1.0, "login": "sorra", "avatarUrl": "https://avatars1.githubusercontent.com/u/1264698?v=4", "isHireable": false, "company": "", "location": "Shanghai", "url": "https://github.com/sorra"}, "joa": {"name": "Joa Ebert", "user": 132653, "commits": 0.0, "issues": 1.0, "commit_comments": 0.0, "issue_comments": 0.0, "pull_requests": 0.0, "pull_request_comments": 0.0, "total": 1.0, "login": "joa", "avatarUrl": "https://avatars2.githubusercontent.com/u/141269?v=4", "isHireable": false, "company": "@maketv", "location": null, "url": "https://github.com/joa"}, "alanyee": {"name": "Alan Yee", "user": 8696808, "commits": 0.0, "issues": 0.0, "commit_comments": 0.0, "issue_comments": 1.0, "pull_requests": 0.0, "pull_request_comments": 0.0, "total": 1.0, "login": "alanyee", "avatarUrl": "https://avatars2.githubusercontent.com/u/1873994?v=4", "isHireable": true, "company": "", "location": "United States", "url": "https://github.com/alanyee"}}