{"nameWithOwner": "twitter/finagle", "reportID": "WEEKLY-REPORT-2022-01-10", "datestamp": {"latest": "2022-01-10", "previous": "2022-01-03"}, "data": {"commits": {"latest": 7830, "previous": 7825, "diff": 5}, "issues": {"latest": 386, "previous": 386, "diff": 0}, "openIssues": {"latest": 47, "previous": 47, "diff": 0}, "closedIssues": {"latest": 339, "previous": 339, "diff": 0}, "pullRequests": {"latest": 533, "previous": 532, "diff": 1}, "openPullRequests": {"latest": 3, "previous": 3, "diff": 0}, "mergedPullRequests": {"latest": 32, "previous": 32, "diff": 0}, "closedPullRequests": {"latest": 498, "previous": 497, "diff": 1}, "forkCount": {"latest": 1388, "previous": 1389, "diff": -1}, "stargazers": {"latest": 8141, "previous": 8132, "diff": 9}, "watchers": {"latest": 569, "previous": 569, "diff": 0}}}