{"nameWithOwner": "twitter/finagle", "reportID": "WEEKLY-REPORT-2018-09-21", "datestamp": {"latest": "2018-09-21", "previous": "2018-09-14"}, "data": {"commits": {"latest": 6351, "previous": 6333, "diff": 18}, "issues": {"latest": 309, "previous": 309, "diff": 0}, "openIssues": {"latest": 22, "previous": 22, "diff": 0}, "closedIssues": {"latest": 287, "previous": 287, "diff": 0}, "pullRequests": {"latest": 416, "previous": 413, "diff": 3}, "openPullRequests": {"latest": 1, "previous": 3, "diff": -2}, "mergedPullRequests": {"latest": 32, "previous": 32, "diff": 0}, "closedPullRequests": {"latest": 383, "previous": 378, "diff": 5}, "forkCount": {"latest": 1219, "previous": 1219, "diff": 0}, "stargazers": {"latest": 6680, "previous": 6674, "diff": 6}, "watchers": {"latest": 602, "previous": 602, "diff": 0}}}