{"nameWithOwner": "twitter/finagle", "reportID": "WEEKLY-REPORT-2019-09-27", "datestamp": {"latest": "2019-09-27", "previous": "2019-09-20"}, "data": {"commits": {"latest": 6869, "previous": 6867, "diff": 2}, "issues": {"latest": 336, "previous": 336, "diff": 0}, "openIssues": {"latest": 29, "previous": 29, "diff": 0}, "closedIssues": {"latest": 307, "previous": 307, "diff": 0}, "pullRequests": {"latest": 460, "previous": 457, "diff": 3}, "openPullRequests": {"latest": 5, "previous": 5, "diff": 0}, "mergedPullRequests": {"latest": 32, "previous": 32, "diff": 0}, "closedPullRequests": {"latest": 423, "previous": 420, "diff": 3}, "forkCount": {"latest": 1294, "previous": 1290, "diff": 4}, "stargazers": {"latest": 7289, "previous": 7285, "diff": 4}, "watchers": {"latest": 592, "previous": 593, "diff": -1}}}