{"nameWithOwner": "twitter/algebird", "reportID": "MONTHLY-REPORT-2024-04-01", "datestamp": {"latest": "2024-04-01", "previous": "2024-02-19"}, "data": {"commits": {"latest": 1905, "previous": 1900, "diff": 5}, "issues": {"latest": 238, "previous": 238, "diff": 0}, "openIssues": {"latest": 72, "previous": 72, "diff": 0}, "closedIssues": {"latest": 166, "previous": 166, "diff": 0}, "pullRequests": {"latest": 930, "previous": 920, "diff": 10}, "openPullRequests": {"latest": 29, "previous": 24, "diff": 5}, "mergedPullRequests": {"latest": 760, "previous": 755, "diff": 5}, "closedPullRequests": {"latest": 141, "previous": 141, "diff": 0}, "forkCount": {"latest": 343, "previous": 357, "diff": -14}, "stargazers": {"latest": 2283, "previous": 2275, "diff": 8}, "watchers": {"latest": 235, "previous": 235, "diff": 0}}}