{"nameWithOwner": "twitter/algebird", "reportID": "WEEKLY-REPORT-2023-07-24", "datestamp": {"latest": "2023-07-24", "previous": "2023-07-03"}, "data": {"commits": {"latest": 1878, "previous": 1867, "diff": 11}, "issues": {"latest": 238, "previous": 238, "diff": 0}, "openIssues": {"latest": 72, "previous": 72, "diff": 0}, "closedIssues": {"latest": 166, "previous": 166, "diff": 0}, "pullRequests": {"latest": 897, "previous": 888, "diff": 9}, "openPullRequests": {"latest": 25, "previous": 29, "diff": -4}, "mergedPullRequests": {"latest": 733, "previous": 722, "diff": 11}, "closedPullRequests": {"latest": 139, "previous": 137, "diff": 2}, "forkCount": {"latest": 348, "previous": 348, "diff": 0}, "stargazers": {"latest": 2258, "previous": 2253, "diff": 5}, "watchers": {"latest": 236, "previous": 237, "diff": -1}}}