{"nameWithOwner": "twitter/chill", "reportID": "MONTHLY-REPORT-2019-10-04", "datestamp": {"latest": "2019-10-04", "previous": "2019-09-06"}, "data": {"commits": {"latest": 606, "previous": 591, "diff": 15}, "issues": {"latest": 125, "previous": 125, "diff": 0}, "openIssues": {"latest": 43, "previous": 43, "diff": 0}, "closedIssues": {"latest": 82, "previous": 82, "diff": 0}, "pullRequests": {"latest": 206, "previous": 204, "diff": 2}, "openPullRequests": {"latest": 2, "previous": 3, "diff": -1}, "mergedPullRequests": {"latest": 183, "previous": 181, "diff": 2}, "closedPullRequests": {"latest": 21, "previous": 20, "diff": 1}, "forkCount": {"latest": 111, "previous": 110, "diff": 1}, "stargazers": {"latest": 514, "previous": 511, "diff": 3}, "watchers": {"latest": 145, "previous": 146, "diff": -1}}}