{"nameWithOwner": "twitter/chill", "reportID": "MONTHLY-REPORT-2019-09-06", "datestamp": {"latest": "2019-09-06", "previous": "2019-08-09"}, "data": {"commits": {"latest": 591, "previous": 591, "diff": 0}, "issues": {"latest": 125, "previous": 125, "diff": 0}, "openIssues": {"latest": 43, "previous": 43, "diff": 0}, "closedIssues": {"latest": 82, "previous": 82, "diff": 0}, "pullRequests": {"latest": 204, "previous": 204, "diff": 0}, "openPullRequests": {"latest": 3, "previous": 3, "diff": 0}, "mergedPullRequests": {"latest": 181, "previous": 181, "diff": 0}, "closedPullRequests": {"latest": 20, "previous": 20, "diff": 0}, "forkCount": {"latest": 110, "previous": 109, "diff": 1}, "stargazers": {"latest": 511, "previous": 510, "diff": 1}, "watchers": {"latest": 146, "previous": 146, "diff": 0}}}