{"nameWithOwner": "twitter/twitter-server", "reportID": "MONTHLY-REPORT-2022-05-02", "datestamp": {"latest": "2022-05-02", "previous": "2022-04-04"}, "data": {"commits": {"latest": 968, "previous": 964, "diff": 4}, "issues": {"latest": 37, "previous": 37, "diff": 0}, "openIssues": {"latest": 0, "previous": 0, "diff": 0}, "closedIssues": {"latest": 37, "previous": 37, "diff": 0}, "pullRequests": {"latest": 34, "previous": 34, "diff": 0}, "openPullRequests": {"latest": 0, "previous": 0, "diff": 0}, "mergedPullRequests": {"latest": 0, "previous": 0, "diff": 0}, "closedPullRequests": {"latest": 34, "previous": 34, "diff": 0}, "forkCount": {"latest": 214, "previous": 208, "diff": 6}, "stargazers": {"latest": 1322, "previous": 1290, "diff": 32}, "watchers": {"latest": 193, "previous": 192, "diff": 1}}}