{"nameWithOwner": "twitter/labella.js", "reportID": "MONTHLY-REPORT-2023-07-24", "datestamp": {"latest": "2023-07-24", "previous": "2023-06-26"}, "data": {"commits": {"latest": 174, "previous": 174, "diff": 0}, "issues": {"latest": 18, "previous": 18, "diff": 0}, "openIssues": {"latest": 4, "previous": 4, "diff": 0}, "closedIssues": {"latest": 14, "previous": 14, "diff": 0}, "pullRequests": {"latest": 28, "previous": 28, "diff": 0}, "openPullRequests": {"latest": 13, "previous": 13, "diff": 0}, "mergedPullRequests": {"latest": 8, "previous": 8, "diff": 0}, "closedPullRequests": {"latest": 7, "previous": 7, "diff": 0}, "forkCount": {"latest": 157, "previous": 156, "diff": 1}, "stargazers": {"latest": 3853, "previous": 3851, "diff": 2}, "watchers": {"latest": 82, "previous": 81, "diff": 1}}}