{"nameWithOwner": "twitter/netty-http2", "reportID": "MONTHLY-REPORT-2019-05-10", "datestamp": {"latest": "2019-05-10", "previous": "2019-04-12"}, "data": {"commits": {"latest": 57, "previous": 57, "diff": 0}, "issues": {"latest": 1, "previous": 1, "diff": 0}, "openIssues": {"latest": 1, "previous": 1, "diff": 0}, "closedIssues": {"latest": 0, "previous": 0, "diff": 0}, "pullRequests": {"latest": 11, "previous": 10, "diff": 1}, "openPullRequests": {"latest": 1, "previous": 0, "diff": 1}, "mergedPullRequests": {"latest": 9, "previous": 9, "diff": 0}, "closedPullRequests": {"latest": 1, "previous": 1, "diff": 0}, "forkCount": {"latest": 42, "previous": 40, "diff": 2}, "stargazers": {"latest": 91, "previous": 91, "diff": 0}, "watchers": {"latest": 124, "previous": 125, "diff": -1}}}