{"nameWithOwner": "twitterdev/getting-started-with-r", "reportID": "WEEKLY-REPORT-2020-05-30", "datestamp": {"latest": "2020-05-30", "previous": "2020-05-23"}, "data": {"commits": {"latest": 11, "previous": 11, "diff": 0}, "issues": {"latest": 0, "previous": 0, "diff": 0}, "openIssues": {"latest": 0, "previous": 0, "diff": 0}, "closedIssues": {"latest": 0, "previous": 0, "diff": 0}, "pullRequests": {"latest": 0, "previous": 0, "diff": 0}, "openPullRequests": {"latest": 0, "previous": 0, "diff": 0}, "mergedPullRequests": {"latest": 0, "previous": 0, "diff": 0}, "closedPullRequests": {"latest": 0, "previous": 0, "diff": 0}, "forkCount": {"latest": 1, "previous": 1, "diff": 0}, "stargazers": {"latest": 1, "previous": 1, "diff": 0}, "watchers": {"latest": 17, "previous": 17, "diff": 0}}}