{"nameWithOwner": "twitter/twemoji", "reportID": "WEEKLY-REPORT-2022-12-12", "datestamp": {"latest": "2022-12-12", "previous": "2022-12-05"}, "data": {"commits": {"latest": 424, "previous": 424, "diff": 0}, "issues": {"latest": 391, "previous": 391, "diff": 0}, "openIssues": {"latest": 56, "previous": 57, "diff": -1}, "closedIssues": {"latest": 335, "previous": 334, "diff": 1}, "pullRequests": {"latest": 157, "previous": 156, "diff": 1}, "openPullRequests": {"latest": 15, "previous": 14, "diff": 1}, "mergedPullRequests": {"latest": 82, "previous": 82, "diff": 0}, "closedPullRequests": {"latest": 60, "previous": 60, "diff": 0}, "forkCount": {"latest": 1717, "previous": 1715, "diff": 2}, "stargazers": {"latest": 14944, "previous": 14920, "diff": 24}, "watchers": {"latest": 349, "previous": 349, "diff": 0}}}