{"nameWithOwner": "pantsbuild/pants", "reportID": "MONTHLY-REPORT-2022-05-16", "datestamp": {"latest": "2022-05-16", "previous": "2022-04-18"}, "data": {"commits": {"latest": 11411, "previous": 11269, "diff": 142}, "issues": {"latest": 4292, "previous": 4205, "diff": 87}, "openIssues": {"latest": 515, "previous": 543, "diff": -28}, "closedIssues": {"latest": 3777, "previous": 3662, "diff": 115}, "pullRequests": {"latest": 11186, "previous": 10954, "diff": 232}, "openPullRequests": {"latest": 58, "previous": 54, "diff": 4}, "mergedPullRequests": {"latest": 7633, "previous": 7422, "diff": 211}, "closedPullRequests": {"latest": 3495, "previous": 3478, "diff": 17}, "forkCount": {"latest": 450, "previous": 442, "diff": 8}, "stargazers": {"latest": 1998, "previous": 1966, "diff": 32}, "watchers": {"latest": 66, "previous": 66, "diff": 0}}}