{"nameWithOwner": "twitter/fatcache", "reportID": "MONTHLY-REPORT-2019-09-27", "datestamp": {"latest": "2019-09-27", "previous": "2019-08-30"}, "data": {"commits": {"latest": 41, "previous": 41, "diff": 0}, "issues": {"latest": 17, "previous": 17, "diff": 0}, "openIssues": {"latest": 8, "previous": 8, "diff": 0}, "closedIssues": {"latest": 9, "previous": 9, "diff": 0}, "pullRequests": {"latest": 17, "previous": 17, "diff": 0}, "openPullRequests": {"latest": 2, "previous": 2, "diff": 0}, "mergedPullRequests": {"latest": 13, "previous": 13, "diff": 0}, "closedPullRequests": {"latest": 2, "previous": 2, "diff": 0}, "forkCount": {"latest": 164, "previous": 163, "diff": 1}, "stargazers": {"latest": 1260, "previous": 1258, "diff": 2}, "watchers": {"latest": 218, "previous": 218, "diff": 0}}}